[
  {
    "brand_name": "vivo",
    "model": "Vivo X Fold 3 Pro",
    "price": 46999.0,
    "battery_capacity": 5700.0,
    "ram_capacity": 16,
    "internal_memory": 512.0,
    "screen_size": 8.03,
    "cpu_benchmark": 11525.0,
    "avg_rating": 9.0,
    "ranking": 1,
    "camera_quality": 50.0,
    "weight": 236.0
  },
  {
    "brand_name": "vivo",
    "model": "Vivo X Fold 3 Pro",
    "price": 50000.0,
    "battery_capacity": 5700.0,
    "ram_capacity": 16,
    "internal_memory": 1024.0,
    "screen_size": 8.03,
    "cpu_benchmark": 11525.0,
    "avg_rating": 9.0,
    "ranking": 2,
    "camera_quality": 50.0,
    "weight": 236.0
  },
  {
    "brand_name": "asus",
    "model": "Asus ROG Phone 7",
    "price": 24999.0,
    "battery_capacity": 6000.0,
    "ram_capacity": 18,
    "internal_memory": 256.0,
    "screen_size": 6.78,
    "cpu_benchmark": 9362.0,
    "avg_rating": 8.7,
    "ranking": 3,
    "camera_quality": 50.0,
    "weight": 239.0
  },
  {
    "brand_name": "oppo",
    "model": "OPPO Reno 10 Pro",
    "price": 8000.0,
    "battery_capacity": 5000.0,
    "ram_capacity": 16,
    "internal_memory": 256.0,
    "screen_size": 6.74,
    "cpu_benchmark": 7374.0,
    "avg_rating": 8.6,
    "ranking": 4,
    "camera_quality": 50.0,
    "weight": 186.0
  },
  {
    "brand_name": "vivo",
    "model": "Vivo X200 Pro",
    "price": 64999.0,
    "battery_capacity": 6000.0,
    "ram_capacity": 16,
    "internal_memory": 512.0,
    "screen_size": 6.78,
    "cpu_benchmark": 7855.0,
    "avg_rating": 7.7,
    "ranking": 5,
    "camera_quality": 150.0,
    "weight": 228.0
  },
  {
    "brand_name": "xiaomi",
    "model": "Xiaomi Redmi Note 14 Pro 5G",
    "price": 21499.0,
    "battery_capacity": 5110.0,
    "ram_capacity": 12,
    "internal_memory": 512.0,
    "screen_size": 6.67,
    "cpu_benchmark": 6330.0,
    "avg_rating": 8.0,
    "ranking": 6,
    "camera_quality": 200.0,
    "weight": 190.0
  },
  {
    "brand_name": "oppo",
    "model": "Oppo Reno 10 Pro Plus",
    "price": 10000.0,
    "battery_capacity": 4700.0,
    "ram_capacity": 12,
    "internal_memory": 256.0,
    "screen_size": 6.74,
    "cpu_benchmark": 9362.0,
    "avg_rating": 8.8,
    "ranking": 7,
    "camera_quality": 64.0,
    "weight": 194.0
  },
  {
    "brand_name": "xiaomi",
    "model": "Xiaomi 14 Ultra",
    "price": 73293.0,
    "battery_capacity": 5000.0,
    "ram_capacity": 16,
    "internal_memory": 512.0,
    "screen_size": 6.73,
    "cpu_benchmark": 11525.0,
    "avg_rating": 9.0,
    "ranking": 8,
    "camera_quality": 50.0,
    "weight": 219.0
  },
  {
    "brand_name": "xiaomi",
    "model": "Xiaomi Redmi Note 14 Pro Plus 5G",
    "price": 25999.0,
    "battery_capacity": 5110.0,
    "ram_capacity": 12,
    "internal_memory": 512.0,
    "screen_size": 6.67,
    "cpu_benchmark": 5754.0,
    "avg_rating": 8.0,
    "ranking": 9,
    "camera_quality": 200.0,
    "weight": 205.0
  },
  {
    "brand_name": "vivo",
    "model": "Vivo X100 Pro",
    "price": 54999.0,
    "battery_capacity": 5400.0,
    "ram_capacity": 16,
    "internal_memory": 512.0,
    "screen_size": 6.78,
    "cpu_benchmark": 7855.0,
    "avg_rating": 8.4,
    "ranking": 10,
    "camera_quality": 50.0,
    "weight": 202.0
  },
  {
    "brand_name": "samsung",
    "model": "Samsung Galaxy S24 Ultra",
    "price": 62000.0,
    "battery_capacity": 5100.0,
    "ram_capacity": 12,
    "internal_memory": 256.0,
    "screen_size": 6.8,
    "cpu_benchmark": 10110.0,
    "avg_rating": 8.5,
    "ranking": 11,
    "camera_quality": 200.0,
    "weight": 232.0
  },
  {
    "brand_name": "xiaomi",
    "model": "Xiaomi Mix Fold 3",
    "price": 30000.0,
    "battery_capacity": 4800.0,
    "ram_capacity": 12,
    "internal_memory": 1024.0,
    "screen_size": 8.03,
    "cpu_benchmark": 9112.0,
    "avg_rating": 9.0,
    "ranking": 12,
    "camera_quality": 50.0,
    "weight": 259.0
  },
  {
    "brand_name": "vivo",
    "model": "Vivo T2x 5G",
    "price": 5800.0,
    "battery_capacity": 6000.0,
    "ram_capacity": 8,
    "internal_memory": 128.0,
    "screen_size": 6.58,
    "cpu_benchmark": 4562.0,
    "avg_rating": 8.0,
    "ranking": 13,
    "camera_quality": 50.0,
    "weight": 203.0
  },
  {
    "brand_name": "google",
    "model": "Google Pixel 8 Pro",
    "price": 15899.0,
    "battery_capacity": 5000.0,
    "ram_capacity": 12,
    "internal_memory": 256.0,
    "screen_size": 6.7,
    "cpu_benchmark": 8133.0,
    "avg_rating": 8.0,
    "ranking": 14,
    "camera_quality": 50.0,
    "weight": 213.0
  },
  {
    "brand_name": "oppo",
    "model": "Oppo Find X6 Pro",
    "price": 18000.0,
    "battery_capacity": 4700.0,
    "ram_capacity": 12,
    "internal_memory": 256.0,
    "screen_size": 6.82,
    "cpu_benchmark": 9362.0,
    "avg_rating": 8.7,
    "ranking": 15,
    "camera_quality": 50.0,
    "weight": 216.0
  },
  {
    "brand_name": "oppo",
    "model": "Oppo Reno 8T",
    "price": 8100.0,
    "battery_capacity": 5000.0,
    "ram_capacity": 8,
    "internal_memory": 256.0,
    "screen_size": 6.7,
    "cpu_benchmark": 4243.0,
    "avg_rating": 8.7,
    "ranking": 16,
    "camera_quality": 108.0,
    "weight": 171.0
  },
  {
    "brand_name": "vivo",
    "model": "Vivo Y38 5G",
    "price": 10000.0,
    "battery_capacity": 6000.0,
    "ram_capacity": 8,
    "internal_memory": 256.0,
    "screen_size": 6.68,
    "cpu_benchmark": 4061.0,
    "avg_rating": 9.0,
    "ranking": 17,
    "camera_quality": 50.0,
    "weight": 199.0
  },
  {
    "brand_name": "oppo",
    "model": "OPPO Reno 10",
    "price": 6770.0,
    "battery_capacity": 5000.0,
    "ram_capacity": 8,
    "internal_memory": 256.0,
    "screen_size": 6.7,
    "cpu_benchmark": 4557.0,
    "avg_rating": 8.4,
    "ranking": 18,
    "camera_quality": 64.0,
    "weight": 185.0
  },
  {
    "brand_name": "vivo",
    "model": "Vivo S17 Pro",
    "price": 9500.0,
    "battery_capacity": 5000.0,
    "ram_capacity": 12,
    "internal_memory": 256.0,
    "screen_size": 6.67,
    "cpu_benchmark": 7374.0,
    "avg_rating": 7.7,
    "ranking": 19,
    "camera_quality": 50.0,
    "weight": 188.0
  },
  {
    "brand_name": "xiaomi",
    "model": "Xiaomi Redmi 13 Prime 5G",
    "price": 8999.0,
    "battery_capacity": 5100.0,
    "ram_capacity": 6,
    "internal_memory": 128.0,
    "screen_size": 6.73,
    "cpu_benchmark": 4061.0,
    "avg_rating": 7.9,
    "ranking": 20,
    "camera_quality": 108.0,
    "weight": 205.0
  },
  {
    "brand_name": "nokia",
    "model": "Nokia X60 5G",
    "price": 9798.0,
    "battery_capacity": 6000.0,
    "ram_capacity": 6,
    "internal_memory": 128.0,
    "screen_size": 6.51,
    "cpu_benchmark": 4889.0,
    "avg_rating": 8.7,
    "ranking": 21,
    "camera_quality": 108.0,
    "weight": 220.0
  },
  {
    "brand_name": "nokia",
    "model": "Nokia X60 Pro 5G",
    "price": 10200.0,
    "battery_capacity": 6000.0,
    "ram_capacity": 8,
    "internal_memory": 128.0,
    "screen_size": 6.51,
    "cpu_benchmark": 4889.0,
    "avg_rating": 0.0,
    "ranking": 22,
    "camera_quality": 108.0,
    "weight": 204.0
  },
  {
    "brand_name": "vivo",
    "model": "Vivo X Fold 2",
    "price": 22999.0,
    "battery_capacity": 4800.0,
    "ram_capacity": 12,
    "internal_memory": 256.0,
    "screen_size": 8.03,
    "cpu_benchmark": 11789.0,
    "avg_rating": 8.0,
    "ranking": 23,
    "camera_quality": 50.0,
    "weight": 279.0
  },
  {
    "brand_name": "xiaomi",
    "model": "Xiaomi Redmi Note 14 Pro",
    "price": 17178.0,
    "battery_capacity": 5500.0,
    "ram_capacity": 8,
    "internal_memory": 256.0,
    "screen_size": 6.67,
    "cpu_benchmark": 6330.0,
    "avg_rating": 8.0,
    "ranking": 24,
    "camera_quality": 200.0,
    "weight": 180.0
  },
  {
    "brand_name": "vivo",
    "model": "Vivo X200",
    "price": 40000.0,
    "battery_capacity": 5800.0,
    "ram_capacity": 12,
    "internal_memory": 256.0,
    "screen_size": 6.67,
    "cpu_benchmark": 7855.0,
    "avg_rating": 7.0,
    "ranking": 25,
    "camera_quality": 150.0,
    "weight": 197.0
  },
  {
    "brand_name": "vivo",
    "model": "Vivo V40",
    "price": 26939.0,
    "battery_capacity": 5500.0,
    "ram_capacity": 12,
    "internal_memory": 256.0,
    "screen_size": 6.78,
    "cpu_benchmark": 6028.0,
    "avg_rating": 8.6,
    "ranking": 26,
    "camera_quality": 50.0,
    "weight": 190.0
  },
  {
    "brand_name": "oppo",
    "model": "Oppo Find X6",
    "price": 8000.0,
    "battery_capacity": 4700.0,
    "ram_capacity": 8,
    "internal_memory": 256.0,
    "screen_size": 6.74,
    "cpu_benchmark": 7878.0,
    "avg_rating": 8.9,
    "ranking": 27,
    "camera_quality": 50.0,
    "weight": 207.0
  },
  {
    "brand_name": "apple",
    "model": "Apple iPhone 16 Pro Max",
    "price": 99999.0,
    "battery_capacity": 4685.0,
    "ram_capacity": 8,
    "internal_memory": 256.0,
    "screen_size": 6.9,
    "cpu_benchmark": 12996.0,
    "avg_rating": 8.2,
    "ranking": 28,
    "camera_quality": 48.0,
    "weight": 227.0
  },
  {
    "brand_name": "vivo",
    "model": "Xiaomi 13 Ultra 5G",
    "price": 45399.0,
    "battery_capacity": 5000.0,
    "ram_capacity": 12,
    "internal_memory": 256.0,
    "screen_size": 6.6,
    "cpu_benchmark": 9112.0,
    "avg_rating": 8.5,
    "ranking": 29,
    "camera_quality": 50.0,
    "weight": 227.0
  },
  {
    "brand_name": "oppo",
    "model": "Oppo A56s",
    "price": 4990.0,
    "battery_capacity": 5000.0,
    "ram_capacity": 8,
    "internal_memory": 128.0,
    "screen_size": 6.56,
    "cpu_benchmark": 4076.0,
    "avg_rating": 7.5,
    "ranking": 30,
    "camera_quality": 13.0,
    "weight": 186.0
  },
  {
    "brand_name": "nokia",
    "model": "Nokia X50 5G",
    "price": 7198.0,
    "battery_capacity": 6000.0,
    "ram_capacity": 6,
    "internal_memory": 64.0,
    "screen_size": 6.81,
    "cpu_benchmark": 5644.0,
    "avg_rating": 7.6,
    "ranking": 31,
    "camera_quality": 108.0,
    "weight": 220.0
  },
  {
    "brand_name": "vivo",
    "model": "Vivo Y100 5G",
    "price": 12000.0,
    "battery_capacity": 4500.0,
    "ram_capacity": 12,
    "internal_memory": 512.0,
    "screen_size": 6.67,
    "cpu_benchmark": 4061.0,
    "avg_rating": 8.0,
    "ranking": 32,
    "camera_quality": 50.0,
    "weight": 185.0
  },
  {
    "brand_name": "vivo",
    "model": "Vivo V26 Pro",
    "price": 15000.0,
    "battery_capacity": 4800.0,
    "ram_capacity": 12,
    "internal_memory": 256.0,
    "screen_size": 6.7,
    "cpu_benchmark": 7878.0,
    "avg_rating": 8.7,
    "ranking": 33,
    "camera_quality": 64.0,
    "weight": 181.0
  },
  {
    "brand_name": "vivo",
    "model": "Vivo V27 Pro",
    "price": 15000.0,
    "battery_capacity": 5000.0,
    "ram_capacity": 12,
    "internal_memory": 256.0,
    "screen_size": 6.73,
    "cpu_benchmark": 7374.0,
    "avg_rating": 8.7,
    "ranking": 34,
    "camera_quality": 50.0,
    "weight": 182.0
  },
  {
    "brand_name": "samsung",
    "model": "Samsung Galaxy S23 Ultra 5G",
    "price": 49999.0,
    "battery_capacity": 5000.0,
    "ram_capacity": 8,
    "internal_memory": 256.0,
    "screen_size": 6.7,
    "cpu_benchmark": 9362.0,
    "avg_rating": 8.5,
    "ranking": 35,
    "camera_quality": 200.0,
    "weight": 234.0
  },
  {
    "brand_name": "xiaomi",
    "model": "Xiaomi Civi 3",
    "price": 10000.0,
    "battery_capacity": 5000.0,
    "ram_capacity": 8,
    "internal_memory": 256.0,
    "screen_size": 6.7,
    "cpu_benchmark": 7374.0,
    "avg_rating": 8.6,
    "ranking": 36,
    "camera_quality": 50.0,
    "weight": 174.0
  },
  {
    "brand_name": "xiaomi",
    "model": "Xiaomi Poco X7",
    "price": 18499.0,
    "battery_capacity": 5110.0,
    "ram_capacity": 8,
    "internal_memory": 256.0,
    "screen_size": 6.67,
    "cpu_benchmark": 6330.0,
    "avg_rating": 8.0,
    "ranking": 37,
    "camera_quality": 50.0,
    "weight": 185.0
  },
  {
    "brand_name": "xiaomi",
    "model": "Xiaomi Redmi Note 14 5G",
    "price": 13699.0,
    "battery_capacity": 5110.0,
    "ram_capacity": 6,
    "internal_memory": 128.0,
    "screen_size": 6.67,
    "cpu_benchmark": 4565.0,
    "avg_rating": 7.5,
    "ranking": 38,
    "camera_quality": 108.0,
    "weight": 190.0
  },
  {
    "brand_name": "xiaomi",
    "model": "Xiaomi 14",
    "price": 40000.0,
    "battery_capacity": 5000.0,
    "ram_capacity": 12,
    "internal_memory": 256.0,
    "screen_size": 6.43,
    "cpu_benchmark": 11525.0,
    "avg_rating": 8.9,
    "ranking": 39,
    "camera_quality": 50.0,
    "weight": 193.0
  },
  {
    "brand_name": "xiaomi",
    "model": "Xiaomi Redmi Note 14",
    "price": 13699.0,
    "battery_capacity": 5500.0,
    "ram_capacity": 8,
    "internal_memory": 128.0,
    "screen_size": 6.67,
    "cpu_benchmark": 4565.0,
    "avg_rating": 7.5,
    "ranking": 40,
    "camera_quality": 108.0,
    "weight": 196.0
  },
  {
    "brand_name": "xiaomi",
    "model": "Xiaomi Redmi Note 13 Pro Plus 5G",
    "price": 15000.0,
    "battery_capacity": 5200.0,
    "ram_capacity": 6,
    "internal_memory": 128.0,
    "screen_size": 6.67,
    "cpu_benchmark": 5230.0,
    "avg_rating": 8.3,
    "ranking": 41,
    "camera_quality": 200.0,
    "weight": 204.0
  },
  {
    "brand_name": "xiaomi",
    "model": "Xiaomi Redmi 14C",
    "price": 8349.0,
    "battery_capacity": 5160.0,
    "ram_capacity": 8,
    "internal_memory": 256.0,
    "screen_size": 6.88,
    "cpu_benchmark": 2752.0,
    "avg_rating": 7.5,
    "ranking": 42,
    "camera_quality": 50.0,
    "weight": 208.0
  },
  {
    "brand_name": "xiaomi",
    "model": "Xiaomi Poco X7 Pro",
    "price": 22999.0,
    "battery_capacity": 6000.0,
    "ram_capacity": 8,
    "internal_memory": 256.0,
    "screen_size": 6.67,
    "cpu_benchmark": 7424.0,
    "avg_rating": 8.0,
    "ranking": 43,
    "camera_quality": 50.0,
    "weight": 195.0
  },
  {
    "brand_name": "samsung",
    "model": "Samsung Galaxy S23 Plus",
    "price": 43000.0,
    "battery_capacity": 4700.0,
    "ram_capacity": 8,
    "internal_memory": 256.0,
    "screen_size": 6.6,
    "cpu_benchmark": 9362.0,
    "avg_rating": 8.9,
    "ranking": 44,
    "camera_quality": 50.0,
    "weight": 196.0
  },
  {
    "brand_name": "xiaomi",
    "model": "Xiaomi 13T",
    "price": 23915.0,
    "battery_capacity": 5000.0,
    "ram_capacity": 12,
    "internal_memory": 256.0,
    "screen_size": 6.67,
    "cpu_benchmark": 7374.0,
    "avg_rating": 8.7,
    "ranking": 45,
    "camera_quality": 50.0,
    "weight": 197.0
  },
  {
    "brand_name": "apple",
    "model": "Apple iPhone 16 Plus",
    "price": 73999.0,
    "battery_capacity": 4674.0,
    "ram_capacity": 8,
    "internal_memory": 128.0,
    "screen_size": 6.7,
    "cpu_benchmark": 12442.0,
    "avg_rating": 7.9,
    "ranking": 46,
    "camera_quality": 48.0,
    "weight": 199.0
  },
  {
    "brand_name": "vivo",
    "model": "Vivo V30e",
    "price": 25000.0,
    "battery_capacity": 5500.0,
    "ram_capacity": 8,
    "internal_memory": 256.0,
    "screen_size": 6.78,
    "cpu_benchmark": 5832.0,
    "avg_rating": 7.5,
    "ranking": 47,
    "camera_quality": 50.0,
    "weight": 188.0
  },
  {
    "brand_name": "vivo",
    "model": "Vivo V40 Pro",
    "price": 40000.0,
    "battery_capacity": 5500.0,
    "ram_capacity": 8,
    "internal_memory": 256.0,
    "screen_size": 6.78,
    "cpu_benchmark": 7855.0,
    "avg_rating": 9.0,
    "ranking": 48,
    "camera_quality": 50.0,
    "weight": 192.0
  },
  {
    "brand_name": "vivo",
    "model": "Vivo V30",
    "price": 22300.0,
    "battery_capacity": 5000.0,
    "ram_capacity": 12,
    "internal_memory": 256.0,
    "screen_size": 6.78,
    "cpu_benchmark": 6028.0,
    "avg_rating": 7.2,
    "ranking": 49,
    "camera_quality": 50.0,
    "weight": 186.0
  },
  {
    "brand_name": "motorola",
    "model": "Motorola Moto G23",
    "price": 3799.0,
    "battery_capacity": 5000.0,
    "ram_capacity": 4,
    "internal_memory": 128.0,
    "screen_size": 6.5,
    "cpu_benchmark": 1896.0,
    "avg_rating": 7.7,
    "ranking": 50,
    "camera_quality": 50.0,
    "weight": 184.0
  },
  {
    "brand_name": "apple",
    "model": "Apple iPhone 15 Pro Max",
    "price": 85799.0,
    "battery_capacity": 4352.0,
    "ram_capacity": 8,
    "internal_memory": 256.0,
    "screen_size": 6.7,
    "cpu_benchmark": 12246.0,
    "avg_rating": 7.9,
    "ranking": 51,
    "camera_quality": 48.0,
    "weight": 221.0
  },
  {
    "brand_name": "vivo",
    "model": "Vivo X100",
    "price": 30000.0,
    "battery_capacity": 5000.0,
    "ram_capacity": 12,
    "internal_memory": 256.0,
    "screen_size": 6.78,
    "cpu_benchmark": 7855.0,
    "avg_rating": 8.2,
    "ranking": 52,
    "camera_quality": 50.0,
    "weight": 206.0
  },
  {
    "brand_name": "motorola",
    "model": "Motorola Moto G73",
    "price": 9599.0,
    "battery_capacity": 5000.0,
    "ram_capacity": 8,
    "internal_memory": 256.0,
    "screen_size": 6.5,
    "cpu_benchmark": 4838.0,
    "avg_rating": 8.5,
    "ranking": 53,
    "camera_quality": 50.0,
    "weight": 181.0
  },
  {
    "brand_name": "motorola",
    "model": "Motorola Moto G91 5G",
    "price": 10999.0,
    "battery_capacity": 5000.0,
    "ram_capacity": 6,
    "internal_memory": 128.0,
    "screen_size": 6.8,
    "cpu_benchmark": 6074.0,
    "avg_rating": 8.0,
    "ranking": 54,
    "camera_quality": 108.0,
    "weight": 212.0
  },
  {
    "brand_name": "vivo",
    "model": "Vivo V27",
    "price": 15000.0,
    "battery_capacity": 4700.0,
    "ram_capacity": 8,
    "internal_memory": 256.0,
    "screen_size": 6.56,
    "cpu_benchmark": 4686.0,
    "avg_rating": 8.3,
    "ranking": 55,
    "camera_quality": 50.0,
    "weight": 180.0
  },
  {
    "brand_name": "xiaomi",
    "model": "Xiaomi Redmi Note 13 Pro 5G",
    "price": 12000.0,
    "battery_capacity": 5000.0,
    "ram_capacity": 6,
    "internal_memory": 128.0,
    "screen_size": 6.67,
    "cpu_benchmark": 5721.0,
    "avg_rating": 7.8,
    "ranking": 56,
    "camera_quality": 200.0,
    "weight": 187.0
  },
  {
    "brand_name": "oppo",
    "model": "Oppo A98",
    "price": 9599.0,
    "battery_capacity": 5000.0,
    "ram_capacity": 8,
    "internal_memory": 128.0,
    "screen_size": 6.72,
    "cpu_benchmark": 4182.0,
    "avg_rating": 8.7,
    "ranking": 57,
    "camera_quality": 64.0,
    "weight": 192.0
  },
  {
    "brand_name": "vivo",
    "model": "Vivo Y56 5G",
    "price": 9239.0,
    "battery_capacity": 5000.0,
    "ram_capacity": 8,
    "internal_memory": 128.0,
    "screen_size": 6.58,
    "cpu_benchmark": 4076.0,
    "avg_rating": 8.0,
    "ranking": 58,
    "camera_quality": 50.0,
    "weight": 184.0
  },
  {
    "brand_name": "motorola",
    "model": "Motorola Edge 40 Pro 5G",
    "price": 24599.0,
    "battery_capacity": 4800.0,
    "ram_capacity": 8,
    "internal_memory": 128.0,
    "screen_size": 6.67,
    "cpu_benchmark": 9112.0,
    "avg_rating": 8.9,
    "ranking": 59,
    "camera_quality": 50.0,
    "weight": 199.0
  },
  {
    "brand_name": "xiaomi",
    "model": "Xiaomi Redmi 12 5G",
    "price": 9490.0,
    "battery_capacity": 5000.0,
    "ram_capacity": 8,
    "internal_memory": 128.0,
    "screen_size": 6.79,
    "cpu_benchmark": 4061.0,
    "avg_rating": 8.5,
    "ranking": 60,
    "camera_quality": 50.0,
    "weight": 199.0
  },
  {
    "brand_name": "oppo",
    "model": "Oppo A78",
    "price": 9238.0,
    "battery_capacity": 5000.0,
    "ram_capacity": 8,
    "internal_memory": 128.0,
    "screen_size": 6.56,
    "cpu_benchmark": 4076.0,
    "avg_rating": 7.9,
    "ranking": 61,
    "camera_quality": 50.0,
    "weight": 188.0
  },
  {
    "brand_name": "vivo",
    "model": "Vivo Y36 5G",
    "price": 9499.0,
    "battery_capacity": 5000.0,
    "ram_capacity": 8,
    "internal_memory": 128.0,
    "screen_size": 6.64,
    "cpu_benchmark": 4076.0,
    "avg_rating": 8.2,
    "ranking": 62,
    "camera_quality": 50.0,
    "weight": 190.0
  },
  {
    "brand_name": "vivo",
    "model": "Vivo Y27",
    "price": 6093.0,
    "battery_capacity": 5000.0,
    "ram_capacity": 8,
    "internal_memory": 128.0,
    "screen_size": 6.64,
    "cpu_benchmark": 2752.0,
    "avg_rating": 8.0,
    "ranking": 63,
    "camera_quality": 50.0,
    "weight": 190.0
  },
  {
    "brand_name": "vivo",
    "model": "Vivo Y27s",
    "price": 6093.0,
    "battery_capacity": 5000.0,
    "ram_capacity": 8,
    "internal_memory": 128.0,
    "screen_size": 6.64,
    "cpu_benchmark": 3781.0,
    "avg_rating": 8.0,
    "ranking": 64,
    "camera_quality": 50.0,
    "weight": 192.0
  },
  {
    "brand_name": "motorola",
    "model": "Motorola Moto G13",
    "price": 4099.0,
    "battery_capacity": 5000.0,
    "ram_capacity": 4,
    "internal_memory": 128.0,
    "screen_size": 6.5,
    "cpu_benchmark": 2752.0,
    "avg_rating": 7.5,
    "ranking": 65,
    "camera_quality": 50.0,
    "weight": 183.0
  },
  {
    "brand_name": "xiaomi",
    "model": "Xiaomi Redmi 13C",
    "price": 8298.0,
    "battery_capacity": 5000.0,
    "ram_capacity": 8,
    "internal_memory": 256.0,
    "screen_size": 6.74,
    "cpu_benchmark": 2752.0,
    "avg_rating": 7.7,
    "ranking": 66,
    "camera_quality": 50.0,
    "weight": 192.0
  },
  {
    "brand_name": "google",
    "model": "Google Pixel 8",
    "price": 13899.0,
    "battery_capacity": 4830.0,
    "ram_capacity": 8,
    "internal_memory": 128.0,
    "screen_size": 6.2,
    "cpu_benchmark": 8133.0,
    "avg_rating": 7.5,
    "ranking": 67,
    "camera_quality": 50.0,
    "weight": 187.0
  },
  {
    "brand_name": "motorola",
    "model": "Motorola ThinkPhone",
    "price": 12599.0,
    "battery_capacity": 5000.0,
    "ram_capacity": 8,
    "internal_memory": 128.0,
    "screen_size": 6.6,
    "cpu_benchmark": 7290.0,
    "avg_rating": 8.9,
    "ranking": 68,
    "camera_quality": 50.0,
    "weight": 188.0
  },
  {
    "brand_name": "xiaomi",
    "model": "Xiaomi 13T Pro",
    "price": 29402.0,
    "battery_capacity": 5000.0,
    "ram_capacity": 8,
    "internal_memory": 256.0,
    "screen_size": 6.67,
    "cpu_benchmark": 7855.0,
    "avg_rating": 9.0,
    "ranking": 69,
    "camera_quality": 50.0,
    "weight": 206.0
  },
  {
    "brand_name": "vivo",
    "model": "Vivo V28",
    "price": 15000.0,
    "battery_capacity": 5000.0,
    "ram_capacity": 8,
    "internal_memory": 256.0,
    "screen_size": 6.7,
    "cpu_benchmark": 2431.0,
    "avg_rating": 8.4,
    "ranking": 70,
    "camera_quality": 108.0,
    "weight": 185.0
  },
  {
    "brand_name": "vivo",
    "model": "Vivo V29",
    "price": 15000.0,
    "battery_capacity": 5000.0,
    "ram_capacity": 8,
    "internal_memory": 256.0,
    "screen_size": 6.67,
    "cpu_benchmark": 3423.0,
    "avg_rating": 8.4,
    "ranking": 71,
    "camera_quality": 108.0,
    "weight": 186.0
  },
  {
    "brand_name": "samsung",
    "model": "Samsung Galaxy M34 5G",
    "price": 17500.0,
    "battery_capacity": 6000.0,
    "ram_capacity": 6,
    "internal_memory": 128.0,
    "screen_size": 6.5,
    "cpu_benchmark": 4522.0,
    "avg_rating": 8.4,
    "ranking": 72,
    "camera_quality": 50.0,
    "weight": 208.0
  },
  {
    "brand_name": "motorola",
    "model": "Motorola Edge 40 5G",
    "price": 18999.0,
    "battery_capacity": 4200.0,
    "ram_capacity": 8,
    "internal_memory": 128.0,
    "screen_size": 6.55,
    "cpu_benchmark": 9112.0,
    "avg_rating": 8.6,
    "ranking": 73,
    "camera_quality": 50.0,
    "weight": 167.0
  },
  {
    "brand_name": "apple",
    "model": "Apple iPhone 15 Plus",
    "price": 60999.0,
    "battery_capacity": 4532.0,
    "ram_capacity": 8,
    "internal_memory": 128.0,
    "screen_size": 6.7,
    "cpu_benchmark": 11205.0,
    "avg_rating": 7.5,
    "ranking": 74,
    "camera_quality": 48.0,
    "weight": 201.0
  },
  {
    "brand_name": "motorola",
    "model": "Motorola Edge 40 Fusion",
    "price": 21599.0,
    "battery_capacity": 4500.0,
    "ram_capacity": 8,
    "internal_memory": 128.0,
    "screen_size": 6.55,
    "cpu_benchmark": 9112.0,
    "avg_rating": 8.7,
    "ranking": 75,
    "camera_quality": 50.0,
    "weight": 167.0
  },
  {
    "brand_name": "vivo",
    "model": "Vivo T2 5G",
    "price": 8360.0,
    "battery_capacity": 4700.0,
    "ram_capacity": 8,
    "internal_memory": 128.0,
    "screen_size": 6.62,
    "cpu_benchmark": 3219.0,
    "avg_rating": 8.5,
    "ranking": 76,
    "camera_quality": 64.0,
    "weight": 172.0
  },
  {
    "brand_name": "apple",
    "model": "Apple iPhone 15 Pro",
    "price": 63999.0,
    "battery_capacity": 5000.0,
    "ram_capacity": 8,
    "internal_memory": 128.0,
    "screen_size": 6.1,
    "cpu_benchmark": 12246.0,
    "avg_rating": 7.5,
    "ranking": 77,
    "camera_quality": 48.0,
    "weight": 187.0
  },
  {
    "brand_name": "vivo",
    "model": "Vivo Y200 5G",
    "price": 12000.0,
    "battery_capacity": 4800.0,
    "ram_capacity": 8,
    "internal_memory": 256.0,
    "screen_size": 6.67,
    "cpu_benchmark": 3958.0,
    "avg_rating": 8.0,
    "ranking": 78,
    "camera_quality": 64.0,
    "weight": 190.0
  },
  {
    "brand_name": "vivo",
    "model": "Vivo Y55s 2023",
    "price": 9239.0,
    "battery_capacity": 5000.0,
    "ram_capacity": 4,
    "internal_memory": 128.0,
    "screen_size": 6.58,
    "cpu_benchmark": 4076.0,
    "avg_rating": 7.8,
    "ranking": 79,
    "camera_quality": 50.0,
    "weight": 187.0
  },
  {
    "brand_name": "xiaomi",
    "model": "Xiaomi Redmi 12",
    "price": 8199.0,
    "battery_capacity": 5000.0,
    "ram_capacity": 8,
    "internal_memory": 128.0,
    "screen_size": 6.79,
    "cpu_benchmark": 2754.0,
    "avg_rating": 8.3,
    "ranking": 80,
    "camera_quality": 50.0,
    "weight": 198.0
  },
  {
    "brand_name": "vivo",
    "model": "Vivo Y78 5G",
    "price": 9135.0,
    "battery_capacity": 4500.0,
    "ram_capacity": 8,
    "internal_memory": 128.0,
    "screen_size": 6.58,
    "cpu_benchmark": 4559.0,
    "avg_rating": 7.7,
    "ranking": 81,
    "camera_quality": 64.0,
    "weight": 177.0
  },
  {
    "brand_name": "xiaomi",
    "model": "Xiaomi Redmi K60 Gaming Edition",
    "price": 20000.0,
    "battery_capacity": 5000.0,
    "ram_capacity": 8,
    "internal_memory": 128.0,
    "screen_size": 6.73,
    "cpu_benchmark": 7290.0,
    "avg_rating": 8.6,
    "ranking": 82,
    "camera_quality": 48.0,
    "weight": 201.0
  },
  {
    "brand_name": "apple",
    "model": "Apple iPhone 16 Pro",
    "price": 82999.0,
    "battery_capacity": 3582.0,
    "ram_capacity": 8,
    "internal_memory": 128.0,
    "screen_size": 6.27,
    "cpu_benchmark": 12996.0,
    "avg_rating": 8.1,
    "ranking": 83,
    "camera_quality": 48.0,
    "weight": 199.0
  },
  {
    "brand_name": "xiaomi",
    "model": "Xiaomi Redmi Note 12 4G",
    "price": 5000.0,
    "battery_capacity": 5000.0,
    "ram_capacity": 4,
    "internal_memory": 64.0,
    "screen_size": 6.67,
    "cpu_benchmark": 3781.0,
    "avg_rating": 7.5,
    "ranking": 84,
    "camera_quality": 50.0,
    "weight": 183.0
  },
  {
    "brand_name": "samsung",
    "model": "Samsung Galaxy A05",
    "price": 5040.0,
    "battery_capacity": 5000.0,
    "ram_capacity": 4,
    "internal_memory": 64.0,
    "screen_size": 6.7,
    "cpu_benchmark": 2752.0,
    "avg_rating": 6.3,
    "ranking": 85,
    "camera_quality": 50.0,
    "weight": 195.0
  },
  {
    "brand_name": "xiaomi",
    "model": "Xiaomi Redmi Note 12 Turbo",
    "price": 10938.0,
    "battery_capacity": 5000.0,
    "ram_capacity": 8,
    "internal_memory": 128.0,
    "screen_size": 6.67,
    "cpu_benchmark": 3853.0,
    "avg_rating": 8.1,
    "ranking": 86,
    "camera_quality": 64.0,
    "weight": 181.0
  },
  {
    "brand_name": "oppo",
    "model": "OPPO F23 Pro",
    "price": 12549.0,
    "battery_capacity": 4500.0,
    "ram_capacity": 8,
    "internal_memory": 128.0,
    "screen_size": 6.72,
    "cpu_benchmark": 4182.0,
    "avg_rating": 8.2,
    "ranking": 87,
    "camera_quality": 64.0,
    "weight": 192.0
  },
  {
    "brand_name": "samsung",
    "model": "Samsung Galaxy A14 5G",
    "price": 8300.0,
    "battery_capacity": 5000.0,
    "ram_capacity": 4,
    "internal_memory": 64.0,
    "screen_size": 6.6,
    "cpu_benchmark": 4120.0,
    "avg_rating": 7.5,
    "ranking": 88,
    "camera_quality": 50.0,
    "weight": 202.0
  },
  {
    "brand_name": "xiaomi",
    "model": "Xiaomi 13 Lite",
    "price": 19700.0,
    "battery_capacity": 4500.0,
    "ram_capacity": 8,
    "internal_memory": 256.0,
    "screen_size": 6.55,
    "cpu_benchmark": 5502.0,
    "avg_rating": 5.6,
    "ranking": 89,
    "camera_quality": 50.0,
    "weight": 171.0
  },
  {
    "brand_name": "vivo",
    "model": "Vivo T2 Pro 5G",
    "price": 9200.0,
    "battery_capacity": 4500.0,
    "ram_capacity": 8,
    "internal_memory": 128.0,
    "screen_size": 6.44,
    "cpu_benchmark": 4686.0,
    "avg_rating": 7.6,
    "ranking": 90,
    "camera_quality": 64.0,
    "weight": 175.0
  },
  {
    "brand_name": "apple",
    "model": "Apple iPhone 16",
    "price": 64999.0,
    "battery_capacity": 3561.0,
    "ram_capacity": 8,
    "internal_memory": 128.0,
    "screen_size": 6.1,
    "cpu_benchmark": 12442.0,
    "avg_rating": 8.0,
    "ranking": 91,
    "camera_quality": 48.0,
    "weight": 170.0
  },
  {
    "brand_name": "xiaomi",
    "model": "Xiaomi Redmi A3",
    "price": 5390.0,
    "battery_capacity": 5000.0,
    "ram_capacity": 4,
    "internal_memory": 128.0,
    "screen_size": 6.71,
    "cpu_benchmark": 1638.0,
    "avg_rating": 7.5,
    "ranking": 92,
    "camera_quality": 8.0,
    "weight": 200.0
  },
  {
    "brand_name": "samsung",
    "model": "Samsung Galaxy A54 5G",
    "price": 18000.0,
    "battery_capacity": 5000.0,
    "ram_capacity": 6,
    "internal_memory": 128.0,
    "screen_size": 6.4,
    "cpu_benchmark": 5023.0,
    "avg_rating": 7.6,
    "ranking": 93,
    "camera_quality": 50.0,
    "weight": 202.0
  },
  {
    "brand_name": "samsung",
    "model": "Samsung Galaxy A15",
    "price": 9100.0,
    "battery_capacity": 5000.0,
    "ram_capacity": 6,
    "internal_memory": 64.0,
    "screen_size": 6.5,
    "cpu_benchmark": 4255.0,
    "avg_rating": 6.3,
    "ranking": 94,
    "camera_quality": 50.0,
    "weight": 200.0
  },
  {
    "brand_name": "xiaomi",
    "model": "Xiaomi Redmi A2",
    "price": 4500.0,
    "battery_capacity": 5000.0,
    "ram_capacity": 2,
    "internal_memory": 32.0,
    "screen_size": 6.52,
    "cpu_benchmark": 1638.0,
    "avg_rating": 7.5,
    "ranking": 95,
    "camera_quality": 8.0,
    "weight": 192.0
  },
  {
    "brand_name": "samsung",
    "model": "Samsung Galaxy M14",
    "price": 10800.0,
    "battery_capacity": 6000.0,
    "ram_capacity": 4,
    "internal_memory": 64.0,
    "screen_size": 6.5,
    "cpu_benchmark": 6103.0,
    "avg_rating": 6.0,
    "ranking": 96,
    "camera_quality": 50.0,
    "weight": 206.0
  },
  {
    "brand_name": "vivo",
    "model": "Vivo Y100",
    "price": 12000.0,
    "battery_capacity": 4500.0,
    "ram_capacity": 8,
    "internal_memory": 128.0,
    "screen_size": 6.38,
    "cpu_benchmark": 4833.0,
    "avg_rating": 7.0,
    "ranking": 97,
    "camera_quality": 50.0,
    "weight": 181.0
  },
  {
    "brand_name": "xiaomi",
    "model": "Xiaomi Redmi A2 Plus",
    "price": 5000.0,
    "battery_capacity": 5000.0,
    "ram_capacity": 2,
    "internal_memory": 32.0,
    "screen_size": 6.52,
    "cpu_benchmark": 1638.0,
    "avg_rating": 7.6,
    "ranking": 98,
    "camera_quality": 8.0,
    "weight": 192.0
  },
  {
    "brand_name": "samsung",
    "model": "Samsung Galaxy S23",
    "price": 34900.0,
    "battery_capacity": 3900.0,
    "ram_capacity": 8,
    "internal_memory": 128.0,
    "screen_size": 6.1,
    "cpu_benchmark": 9362.0,
    "avg_rating": 8.8,
    "ranking": 99,
    "camera_quality": 50.0,
    "weight": 168.0
  },
  {
    "brand_name": "samsung",
    "model": "Samsung Galaxy A24",
    "price": 9950.0,
    "battery_capacity": 4000.0,
    "ram_capacity": 6,
    "internal_memory": 64.0,
    "screen_size": 6.4,
    "cpu_benchmark": 4255.0,
    "avg_rating": 7.7,
    "ranking": 100,
    "camera_quality": 50.0,
    "weight": 195.0
  },
  {
    "brand_name": "motorola",
    "model": "Motorola Moto E13",
    "price": 5499.0,
    "battery_capacity": 5000.0,
    "ram_capacity": 2,
    "internal_memory": 64.0,
    "screen_size": 6.5,
    "cpu_benchmark": 2555.0,
    "avg_rating": 6.5,
    "ranking": 101,
    "camera_quality": 13.0,
    "weight": 179.0
  },
  {
    "brand_name": "apple",
    "model": "Apple iPhone 15",
    "price": 52999.0,
    "battery_capacity": 3285.0,
    "ram_capacity": 6,
    "internal_memory": 128.0,
    "screen_size": 6.1,
    "cpu_benchmark": 11205.0,
    "avg_rating": 7.2,
    "ranking": 102,
    "camera_quality": 48.0,
    "weight": 171.0
  },
  {
    "brand_name": "samsung",
    "model": "Samsung Galaxy S23 FE 5G",
    "price": 23700.0,
    "battery_capacity": 4500.0,
    "ram_capacity": 8,
    "internal_memory": 128.0,
    "screen_size": 6.4,
    "cpu_benchmark": 5783.0,
    "avg_rating": 7.7,
    "ranking": 103,
    "camera_quality": 50.0,
    "weight": 209.0
  },
  {
    "brand_name": "google",
    "model": "Google Pixel 7A",
    "price": 12500.0,
    "battery_capacity": 4410.0,
    "ram_capacity": 6,
    "internal_memory": 128.0,
    "screen_size": 6.1,
    "cpu_benchmark": 7380.0,
    "avg_rating": 6.9,
    "ranking": 104,
    "camera_quality": 64.0,
    "weight": 193.0
  }
]
